main.py
utils.py
dbtcpy-1.2.1.dist-info/LICENSE
dbtcpy-1.2.1.dist-info/METADATA
dbtcpy-1.2.1.dist-info/WHEEL
dbtcpy-1.2.1.dist-info/top_level.txt
dbtcpy-1.2.1.dist-info/RECORD
