Metadata-Version: 2.1
Name: dbtcpy
Version: 1.2.1
Summary: Open source library in python3 to freely manage databases.
Author-email: xLitus <xLitus@protestant.com>
Project-URL: Homepage, https://github.com/xLitus/dbtcpy
Project-URL: Issues, https://github.com/xLitus/dbtcpy/issues
Classifier: Programming Language :: Python :: 3
Classifier: License :: OSI Approved :: MIT License
Classifier: Operating System :: OS Independent
Requires-Python: >=3.8
License-File: LICENSE
